nmoo/__init__.py
nmoo/__main__.py
nmoo/benchmark.py
nmoo/delayer.py
nmoo/lambda.py
nmoo/wrapped_problem.py
nmoo/algorithms/__init__.py
nmoo/algorithms/ar_nsga2.py
nmoo/callbacks/__init__.py
nmoo/callbacks/timer_callback.py
nmoo/denoisers/__init__.py
nmoo/denoisers/gpss.py
nmoo/denoisers/knnavg.py
nmoo/denoisers/resample_average.py
nmoo/evaluators/__init__.py
nmoo/evaluators/penalized_evaluator.py
nmoo/indicators/__init__.py
nmoo/indicators/delta_f.py
nmoo/noises/__init__.py
nmoo/noises/gaussian.py
nmoo/noises/uniform.py
nmoo/plotting/__init__.py
nmoo/plotting/delta_f.py
nmoo/plotting/performance_indicators.py
nmoo/utils/__init__.py
nmoo/utils/population.py
nmoo-5.1.0.dist-info/LICENSE
nmoo-5.1.0.dist-info/METADATA
nmoo-5.1.0.dist-info/WHEEL
nmoo-5.1.0.dist-info/entry_points.txt
nmoo-5.1.0.dist-info/top_level.txt
nmoo-5.1.0.dist-info/RECORD
