Metadata-Version: 2.1
Name: nmoo
Version: 5.1.0
Summary: A wrapper-based framework for pymoo problem modification.
Home-page: https://github.com/altaris/noisy-moo
Author: Cédric HT
Author-email: hothanh@nii.ac.jp
Project-URL: Issues, https://github.com/altaris/noisy-moo/issues
Platform: any
Classifier: Intended Audience :: Developers
Classifier: Intended Audience :: Science/Research
Classifier: License :: OSI Approved :: MIT License
Classifier: Operating System :: OS Independent
Classifier: Programming Language :: Python :: 3
Classifier: Programming Language :: Python :: 3.7
Classifier: Programming Language :: Python :: 3.8
Classifier: Programming Language :: Python :: 3.9
Classifier: Programming Language :: Python :: 3.10
Classifier: Topic :: Scientific/Engineering :: Mathematics
Classifier: Topic :: Scientific/Engineering
Requires-Python: >=3.7
License-File: LICENSE
Requires-Dist: click
Requires-Dist: gradient-free-optimizers
Requires-Dist: joblib
Requires-Dist: numpy
Requires-Dist: pandas
Requires-Dist: pymoo (==0.5.0)
Requires-Dist: seaborn
